{
    "swagger": "2.0",
    "info": {
        "description": "API Server for TODO Application",
        "title": "Todo App API",
        "contact": {},
        "version": "1.0"
    },
    "host": "localhost:8001",
    "basePath": "/",
    "paths": {
        "/api/items/:id": {
            "get": {
                "security": [
                    {
                        "apiKeyAuth": []
                    }
                ],
                "description": "return item by ID of current user",
                "produces": [
                    "application/json"
                ],
                "tags": [
                    "items"
                ],
                "summary": "Get TODO Items By ID",
                "operationId": "get-todo-item-by-id",
                "responses": {
                    "200": {
                        "description": "OK",
                        "schema": {
                            "$ref": "#/definitions/todoapp.TodoItem"
                        }
                    },
                    "400": {
                        "description": "Bad Request",
                        "schema": {
                            "$ref": "#/definitions/handler.errorResponse"
                        }
                    },
                    "404": {
                        "description": "Not Found",
                        "schema": {
                            "$ref": "#/definitions/handler.errorResponse"
                        }
                    },
                    "500": {
                        "description": "Internal Server Error",
                        "schema": {
                            "$ref": "#/definitions/handler.errorResponse"
                        }
                    },
                    "default": {
                        "description": "",
                        "schema": {
                            "$ref": "#/definitions/handler.errorResponse"
                        }
                    }
                }
            },
            "put": {
                "security": [
                    {
                        "apiKeyAuth": []
                    }
                ],
                "description": "update item by ID of current user",
                "produces": [
                    "application/json"
                ],
                "tags": [
                    "items"
                ],
                "summary": "Update TODO Items By ID",
                "operationId": "update-todo-item",
                "parameters": [
                    {
                        "description": "updated item info",
                        "name": "payload",
                        "in": "body",
                        "required": true,
                        "schema": {
                            "$ref": "#/definitions/todoapp.UpdateItemInput"
                        }
                    }
                ],
                "responses": {
                    "200": {
                        "description": "status",
                        "schema": {
                            "type": "string"
                        }
                    },
                    "400": {
                        "description": "Bad Request",
                        "schema": {
                            "$ref": "#/definitions/handler.errorResponse"
                        }
                    },
                    "404": {
                        "description": "Not Found",
                        "schema": {
                            "$ref": "#/definitions/handler.errorResponse"
                        }
                    },
                    "500": {
                        "description": "Internal Server Error",
                        "schema": {
                            "$ref": "#/definitions/handler.errorResponse"
                        }
                    },
                    "default": {
                        "description": "",
                        "schema": {
                            "$ref": "#/definitions/handler.errorResponse"
                        }
                    }
                }
            },
            "delete": {
                "security": [
                    {
                        "apiKeyAuth": []
                    }
                ],
                "description": "delete item by ID of current user",
                "produces": [
                    "application/json"
                ],
                "tags": [
                    "items"
                ],
                "summary": "Delete TODO Items By ID",
                "operationId": "delete-todo-item",
                "responses": {
                    "200": {
                        "description": "status",
                        "schema": {
                            "type": "string"
                        }
                    },
                    "400": {
                        "description": "Bad Request",
                        "schema": {
                            "$ref": "#/definitions/handler.errorResponse"
                        }
                    },
                    "404": {
                        "description": "Not Found",
                        "schema": {
                            "$ref": "#/definitions/handler.errorResponse"
                        }
                    },
                    "500": {
                        "description": "Internal Server Error",
                        "schema": {
                            "$ref": "#/definitions/handler.errorResponse"
                        }
                    },
                    "default": {
                        "description": "",
                        "schema": {
                            "$ref": "#/definitions/handler.errorResponse"
                        }
                    }
                }
            }
        },
        "/api/lists": {
            "post": {
                "security": [
                    {
                        "ApiKeyAuth": []
                    }
                ],
                "description": "create new list for current user",
                "consumes": [
                    "application/json"
                ],
                "produces": [
                    "application/json"
                ],
                "tags": [
                    "lists"
                ],
                "summary": "Create TODO List",
                "operationId": "create-list",
                "parameters": [
                    {
                        "description": "list info",
                        "name": "payload",
                        "in": "body",
                        "required": true,
                        "schema": {
                            "$ref": "#/definitions/todoapp.TodoList"
                        }
                    }
                ],
                "responses": {
                    "200": {
                        "description": "OK",
                        "schema": {
                            "type": "integer"
                        }
                    },
                    "400": {
                        "description": "Bad Request",
                        "schema": {
                            "$ref": "#/definitions/handler.errorResponse"
                        }
                    },
                    "404": {
                        "description": "Not Found",
                        "schema": {
                            "$ref": "#/definitions/handler.errorResponse"
                        }
                    },
                    "500": {
                        "description": "Internal Server Error",
                        "schema": {
                            "$ref": "#/definitions/handler.errorResponse"
                        }
                    },
                    "default": {
                        "description": "",
                        "schema": {
                            "$ref": "#/definitions/handler.errorResponse"
                        }
                    }
                }
            }
        },
        "/api/lists/:id": {
            "get": {
                "security": [
                    {
                        "apiKeyAuth": []
                    }
                ],
                "description": "Get TODO List By choosen ID",
                "produces": [
                    "application/json"
                ],
                "tags": [
                    "lists"
                ],
                "summary": "Get TODO List By ID",
                "operationId": "get-list-by-id",
                "responses": {
                    "200": {
                        "description": "OK",
                        "schema": {
                            "$ref": "#/definitions/todoapp.TodoList"
                        }
                    },
                    "400": {
                        "description": "Bad Request",
                        "schema": {
                            "$ref": "#/definitions/handler.errorResponse"
                        }
                    },
                    "404": {
                        "description": "Not Found",
                        "schema": {
                            "$ref": "#/definitions/handler.errorResponse"
                        }
                    },
                    "500": {
                        "description": "Internal Server Error",
                        "schema": {
                            "$ref": "#/definitions/handler.errorResponse"
                        }
                    },
                    "default": {
                        "description": "",
                        "schema": {
                            "$ref": "#/definitions/handler.errorResponse"
                        }
                    }
                }
            },
            "put": {
                "security": [
                    {
                        "ApiKeyAuth": []
                    }
                ],
                "description": "Update choosen list info",
                "consumes": [
                    "application/json"
                ],
                "produces": [
                    "application/json"
                ],
                "tags": [
                    "lists"
                ],
                "summary": "Update TODO List",
                "operationId": "update-list",
                "responses": {
                    "200": {
                        "description": "status",
                        "schema": {
                            "type": "string"
                        }
                    },
                    "400": {
                        "description": "Bad Request",
                        "schema": {
                            "$ref": "#/definitions/handler.errorResponse"
                        }
                    },
                    "404": {
                        "description": "Not Found",
                        "schema": {
                            "$ref": "#/definitions/handler.errorResponse"
                        }
                    },
                    "500": {
                        "description": "Internal Server Error",
                        "schema": {
                            "$ref": "#/definitions/handler.errorResponse"
                        }
                    },
                    "default": {
                        "description": "",
                        "schema": {
                            "$ref": "#/definitions/handler.errorResponse"
                        }
                    }
                }
            },
            "delete": {
                "security": [
                    {
                        "apiKeyAuth": []
                    }
                ],
                "description": "Delete TODO List",
                "produces": [
                    "application/json"
                ],
                "tags": [
                    "lists"
                ],
                "summary": "Delete TODO List",
                "operationId": "delete-todo-list",
                "responses": {
                    "200": {
                        "description": "status",
                        "schema": {
                            "type": "string"
                        }
                    },
                    "400": {
                        "description": "Bad Request",
                        "schema": {
                            "$ref": "#/definitions/handler.errorResponse"
                        }
                    },
                    "404": {
                        "description": "Not Found",
                        "schema": {
                            "$ref": "#/definitions/handler.errorResponse"
                        }
                    },
                    "500": {
                        "description": "Internal Server Error",
                        "schema": {
                            "$ref": "#/definitions/handler.errorResponse"
                        }
                    },
                    "default": {
                        "description": "",
                        "schema": {
                            "$ref": "#/definitions/handler.errorResponse"
                        }
                    }
                }
            }
        },
        "/api/lists/:id/items": {
            "get": {
                "security": [
                    {
                        "apiKeyAuth": []
                    }
                ],
                "description": "return all items from choosen list of current user",
                "produces": [
                    "application/json"
                ],
                "tags": [
                    "items"
                ],
                "summary": "Get All TODO Items",
                "operationId": "get-all-todo-items",
                "responses": {
                    "200": {
                        "description": "OK",
                        "schema": {
                            "type": "object"
                        }
                    },
                    "400": {
                        "description": "Bad Request",
                        "schema": {
                            "$ref": "#/definitions/handler.errorResponse"
                        }
                    },
                    "404": {
                        "description": "Not Found",
                        "schema": {
                            "$ref": "#/definitions/handler.errorResponse"
                        }
                    },
                    "500": {
                        "description": "Internal Server Error",
                        "schema": {
                            "$ref": "#/definitions/handler.errorResponse"
                        }
                    },
                    "default": {
                        "description": "",
                        "schema": {
                            "$ref": "#/definitions/handler.errorResponse"
                        }
                    }
                }
            },
            "post": {
                "security": [
                    {
                        "apiKeyAuth": []
                    }
                ],
                "description": "will create new item in list of current user",
                "produces": [
                    "application/json"
                ],
                "tags": [
                    "items"
                ],
                "summary": "Create TODO Item",
                "operationId": "create-todo-item",
                "parameters": [
                    {
                        "description": "item info",
                        "name": "payload",
                        "in": "body",
                        "required": true,
                        "schema": {
                            "$ref": "#/definitions/todoapp.TodoItem"
                        }
                    }
                ],
                "responses": {
                    "200": {
                        "description": "id",
                        "schema": {
                            "type": "string"
                        }
                    },
                    "400": {
                        "description": "Bad Request",
                        "schema": {
                            "$ref": "#/definitions/handler.errorResponse"
                        }
                    },
                    "404": {
                        "description": "Not Found",
                        "schema": {
                            "$ref": "#/definitions/handler.errorResponse"
                        }
                    },
                    "500": {
                        "description": "Internal Server Error",
                        "schema": {
                            "$ref": "#/definitions/handler.errorResponse"
                        }
                    },
                    "default": {
                        "description": "",
                        "schema": {
                            "$ref": "#/definitions/handler.errorResponse"
                        }
                    }
                }
            }
        },
        "/auth/sign-in": {
            "post": {
                "description": "return token",
                "consumes": [
                    "application/json"
                ],
                "produces": [
                    "application/json"
                ],
                "tags": [
                    "auth"
                ],
                "summary": "Sign In (Authentication)",
                "parameters": [
                    {
                        "description": "username password",
                        "name": "payload",
                        "in": "body",
                        "required": true,
                        "schema": {
                            "$ref": "#/definitions/handler.signInInput"
                        }
                    }
                ],
                "responses": {
                    "200": {
                        "description": "token",
                        "schema": {
                            "type": "string"
                        }
                    },
                    "400": {
                        "description": "Bad Request",
                        "schema": {
                            "$ref": "#/definitions/handler.errorResponse"
                        }
                    },
                    "404": {
                        "description": "Not Found",
                        "schema": {
                            "$ref": "#/definitions/handler.errorResponse"
                        }
                    },
                    "500": {
                        "description": "Internal Server Error",
                        "schema": {
                            "$ref": "#/definitions/handler.errorResponse"
                        }
                    },
                    "default": {
                        "description": "",
                        "schema": {
                            "$ref": "#/definitions/handler.errorResponse"
                        }
                    }
                }
            }
        },
        "/auth/sign-up": {
            "post": {
                "description": "return created user ID",
                "consumes": [
                    "application/json"
                ],
                "produces": [
                    "application/json"
                ],
                "tags": [
                    "auth"
                ],
                "summary": "Sign Up (Registration)",
                "parameters": [
                    {
                        "description": "account info",
                        "name": "payload",
                        "in": "body",
                        "required": true,
                        "schema": {
                            "$ref": "#/definitions/todoapp.User"
                        }
                    }
                ],
                "responses": {
                    "200": {
                        "description": "OK",
                        "schema": {
                            "type": "integer"
                        }
                    },
                    "400": {
                        "description": "Bad Request",
                        "schema": {
                            "$ref": "#/definitions/handler.errorResponse"
                        }
                    },
                    "404": {
                        "description": "Not Found",
                        "schema": {
                            "$ref": "#/definitions/handler.errorResponse"
                        }
                    },
                    "500": {
                        "description": "Internal Server Error",
                        "schema": {
                            "$ref": "#/definitions/handler.errorResponse"
                        }
                    },
                    "default": {
                        "description": "",
                        "schema": {
                            "$ref": "#/definitions/handler.errorResponse"
                        }
                    }
                }
            }
        }
    },
    "definitions": {
        "handler.errorResponse": {
            "type": "object",
            "properties": {
                "message": {
                    "type": "string"
                }
            }
        },
        "handler.signInInput": {
            "type": "object",
            "required": [
                "password",
                "username"
            ],
            "properties": {
                "password": {
                    "type": "string"
                },
                "username": {
                    "type": "string"
                }
            }
        },
        "todoapp.TodoItem": {
            "type": "object",
            "required": [
                "title"
            ],
            "properties": {
                "description": {
                    "type": "string"
                },
                "done": {
                    "type": "boolean"
                },
                "id": {
                    "type": "integer"
                },
                "title": {
                    "type": "string"
                }
            }
        },
        "todoapp.TodoList": {
            "type": "object",
            "required": [
                "title"
            ],
            "properties": {
                "description": {
                    "type": "string"
                },
                "id": {
                    "type": "integer"
                },
                "title": {
                    "type": "string"
                }
            }
        },
        "todoapp.UpdateItemInput": {
            "type": "object",
            "properties": {
                "description": {
                    "type": "string"
                },
                "done": {
                    "type": "boolean"
                },
                "title": {
                    "type": "string"
                }
            }
        },
        "todoapp.User": {
            "type": "object",
            "required": [
                "name",
                "password",
                "username"
            ],
            "properties": {
                "name": {
                    "type": "string"
                },
                "password": {
                    "type": "string"
                },
                "username": {
                    "type": "string"
                }
            }
        }
    },
    "securityDefinitions": {
        "ApiKeyAuth": {
            "type": "apiKey",
            "name": "Authorization",
            "in": "header"
        }
    }
}